Workbook
Name aporte: Planilha1!$D$16
Name patrimonio: Planilha1!$D$19
Name qtd_anos: Planilha1!$D$17
Name Rendimento_carteira: Planilha1!$D$12
Name salario: Planilha1!$D$11
Name sugestao_investimento: Planilha1!$D$13
Name taxa_mensal: Planilha1!$D$18

Sheet Planilha1
B10: CONFIGURAÇÕES
B11: Salário | D11: 2000
B12: Rendimento Carteira | D12: 0.01
B13: Sugestão de investimento | D13: =D11*30% -> 600
B15: INVESTIMENTO MENSAL
B16: Quanto investir por mês? | D16: 500
B17: Por quantos anos? | D17: 5
B18: Taxa de Rendimentos? | D18: 0.01079
B19: Patrimônio acumulado? | D19: =FV(taxa_mensal,qtd_anos*12,aporte*-1) -> 41888.457
B20: Dividendos Mensais? | D20: =patrimonio*Rendimento_carteira -> 418.88457
B22: CENÁRIOS | D22: DIVIDENDOS
A23: 2 | B23: Quanto em 2 anos? | C23: =FV($D$18,$A23*12,$D$16*-1) -> 13613.814 | D23: =C23*Rendimento_carteira -> 136.13814
A24: 5 | B24: Quanto em 5 anos? | C24: =FV($D$18,$A24*12,$D$16*-1) -> 41888.457 | D24: =C24*Rendimento_carteira -> 418.88457
A25: 10 | B25: Quanto em 10 anos? | C25: =FV($D$18,$A25*12,$D$16*-1) -> 121642.11 | D25: =C25*Rendimento_carteira -> 1216.4211
A26: 20 | B26: Quanto em 20 anos? | C26: =FV($D$18,$A26*12,$D$16*-1) -> 562599.2 | D26: =C26*Rendimento_carteira -> 5625.992
A27: 30 | B27: Quanto em 30 anos? | C27: =FV($D$18,$A27*12,$D$16*-1) -> 2161084.8 | D27: =C27*Rendimento_carteira -> 21610.848
B30: PERFIL | C30: Conservador
B31: VALOR A SER INVESTIDO POR MÊS | C31: =aporte -> 500
B34: TIPO DE FII | C34: Percentual Sugerido | D34: Valores
B35: PAPEL | C35: =VLOOKUP($C$30&"-"&B35,Planilha2!$A$6:$D$23,4,) -> 0.3 | D35: =C35*$C$31 -> 150
B36: TIJOLO | C36: =VLOOKUP($C$30&"-"&B36,Planilha2!$A$6:$D$23,4,) -> 0.5 | D36: =C36*$C$31 -> 250
B37: HIBRIDO | C37: =VLOOKUP($C$30&"-"&B37,Planilha2!$A$6:$D$23,4,) -> 0.1 | D37: =C37*$C$31 -> 50
B38: FOFs | C38: =VLOOKUP($C$30&"-"&B38,Planilha2!$A$6:$D$23,4,) -> 0.1 | D38: =C38*$C$31 -> 50
B39: DESENVOLVIMENTO | C39: =VLOOKUP($C$30&"-"&B39,Planilha2!$A$6:$D$23,4,) -> 0 | D39: =C39*$C$31 -> 0
B40: HOTELARIA | C40: =VLOOKUP($C$30&"-"&B40,Planilha2!$A$6:$D$23,4,) -> 0 | D40: =C40*$C$31 -> 0
D41: =SUM(D35:D40) -> 500

Sheet Planilha2
A5: CHAVE | B5: PERFIL | C5: TIPO DE FII | D5: %
A6: =$B$6&"-"&C6 -> Conservador-PAPEL | B6: Conservador | C6: PAPEL | D6: 0.3 | H6: %
A7: =$B$6&"-"&C7 -> Conservador-TIJOLO | B7: Conservador | C7: TIJOLO | D7: 0.5 | G7: Conservador-PAPEL | H7: =VLOOKUP(G7,$A:$D,2,) -> Conservador
A8: =$B$6&"-"&C8 -> Conservador-HIBRIDO | B8: Conservador | C8: HIBRIDO | D8: 0.1
A9: =$B$6&"-"&C9 -> Conservador-FOFs | B9: Conservador | C9: FOFs | D9: 0.1
A10: =$B$6&"-"&C10 -> Conservador-DESENVOLVIMENTO | B10: Conservador | C10: DESENVOLVIMENTO | D10: 0
A11: =$B$6&"-"&C11 -> Conservador-HOTELARIA | B11: Conservador | C11: HOTELARIA | D11: 0
A12: =$B$6&"-"&C12 -> Conservador-PAPEL | B12: Moderado | C12: PAPEL | D12: 0.32
A13: =$B$6&"-"&C13 -> Conservador-TIJOLO | B13: Moderado | C13: TIJOLO | D13: 0.4
A14: =$B$6&"-"&C14 -> Conservador-HIBRIDO | B14: Moderado | C14: HIBRIDO | D14: 0.08
A15: =$B$6&"-"&C15 -> Conservador-FOFs | B15: Moderado | C15: FOFs | D15: 0.1
A16: =$B$6&"-"&C16 -> Conservador-DESENVOLVIMENTO | B16: Moderado | C16: DESENVOLVIMENTO | D16: 0.1
A17: =$B$6&"-"&C17 -> Conservador-HOTELARIA | B17: Moderado | C17: HOTELARIA | D17: 0.1
A18: =$B$6&"-"&C18 -> Conservador-PAPEL | B18: Agressivo | C18: PAPEL | D18: 0.5
A19: =$B$6&"-"&C19 -> Conservador-TIJOLO | B19: Agressivo | C19: TIJOLO | D19: 0.1
... A23: =$B$6&"-"&C23 -> Conservador-HOTELARIA | B23: Agressivo | C23: HOTELARIA | D23: 0.1
